varius/__init__.py
varius/printer.py
varius/scope.py
varius/variable.py
varius-0.1.10.dist-info/LICENSE
varius-0.1.10.dist-info/METADATA
varius-0.1.10.dist-info/WHEEL
varius-0.1.10.dist-info/top_level.txt
varius-0.1.10.dist-info/RECORD
