Metadata-Version: 2.1
Name: varius
Version: 0.1.10
Summary: Perform calculation with various versions of variables
Home-page: https://chenchaozhao.github.io/varius/
Author: Chenchao Zhao
Author-email: chenchao.zhao@gmail.com
License: MIT
Platform: UNKNOWN
Requires-Dist: sympy
Requires-Dist: dataclasses
